__init__.py
helpers.py
main.py
oracle.py
processors.py
oracle_nft-0.1.6.dist-info/LICENSE
oracle_nft-0.1.6.dist-info/METADATA
oracle_nft-0.1.6.dist-info/WHEEL
oracle_nft-0.1.6.dist-info/top_level.txt
oracle_nft-0.1.6.dist-info/RECORD
