Metadata-Version: 2.1
Name: oracle-nft
Version: 0.1.6
Summary: Open oracle for illiquid collection pricing.
Author-email: Cairo <cairo@gradient.city>
License: MIT License        
Project-URL: Homepage, https://github.com/GradientFinance/oracle
Project-URL: Bug Tracker, https://github.com/GradientFinance/oracle/issues
Classifier: Programming Language :: Python :: 3
Classifier: License :: OSI Approved :: MIT License
Classifier: Operating System :: OS Independent
Requires-Python: >=3.7
License-File: LICENSE
